pyfeather.cpython-38-x86_64-linux-gnu.so
pyfeather-0.0.5.dist-info/RECORD
pyfeather-0.0.5.dist-info/METADATA
pyfeather-0.0.5.dist-info/LICENSE
pyfeather-0.0.5.dist-info/WHEEL
pyfeather-0.0.5.dist-info/top_level.txt
