Metadata-Version: 2.1
Name: pyfeather
Version: 0.0.5
Summary: A project makes feature-hash easier.
Home-page: https://github.com/innerNULL/feather
Author: innerNULL
Author-email: 
License: UNKNOWN
Platform: UNKNOWN
License-File: LICENSE
Provides-Extra: test
Requires-Dist: pytest ; extra == 'test'
